nibiru/__init__.py
nibiru/chain_client.py
nibiru/crypto/__init__.py
nibiru/crypto/ripemd160.py
nibiru/event_specs.py
nibiru/exceptions.py
nibiru/grpc_client.py
nibiru/jsonrpc/__init__.py
nibiru/jsonrpc/jsonrpc.py
nibiru/jsonrpc/rpc_error.py
nibiru/msg/__init__.py
nibiru/msg/bank.py
nibiru/msg/msg.py
nibiru/msg/perp.py
nibiru/msg/spot.py
nibiru/msg/staking.py
nibiru/pytypes/__init__.py
nibiru/pytypes/common.py
nibiru/pytypes/event.py
nibiru/pytypes/jsonable.py
nibiru/pytypes/network.py
nibiru/pytypes/tx_resp.py
nibiru/query_clients/__init__.py
nibiru/query_clients/auth.py
nibiru/query_clients/epoch.py
nibiru/query_clients/perp.py
nibiru/query_clients/spot.py
nibiru/query_clients/stablecoin.py
nibiru/query_clients/staking.py
nibiru/query_clients/util.py
nibiru/tmrpc/__init__.py
nibiru/tmrpc/broadcast.py
nibiru/tx.py
nibiru/utils.py
nibiru/wallet.py
nibiru/websocket.py
nibiru_proto/__init__.py
nibiru_proto/amino/amino_pb2.py
nibiru_proto/amino/amino_pb2.pyi
nibiru_proto/amino/amino_pb2_grpc.py
nibiru_proto/cosmos/app/runtime/v1alpha1/module_pb2.py
nibiru_proto/cosmos/app/runtime/v1alpha1/module_pb2.pyi
nibiru_proto/cosmos/app/runtime/v1alpha1/module_pb2_grpc.py
nibiru_proto/cosmos/app/v1alpha1/config_pb2.py
nibiru_proto/cosmos/app/v1alpha1/config_pb2.pyi
nibiru_proto/cosmos/app/v1alpha1/config_pb2_grpc.py
nibiru_proto/cosmos/app/v1alpha1/module_pb2.py
nibiru_proto/cosmos/app/v1alpha1/module_pb2.pyi
nibiru_proto/cosmos/app/v1alpha1/module_pb2_grpc.py
nibiru_proto/cosmos/app/v1alpha1/query_pb2.py
nibiru_proto/cosmos/app/v1alpha1/query_pb2.pyi
nibiru_proto/cosmos/app/v1alpha1/query_pb2_grpc.py
nibiru_proto/cosmos/auth/module/v1/module_pb2.py
nibiru_proto/cosmos/auth/module/v1/module_pb2.pyi
nibiru_proto/cosmos/auth/module/v1/module_pb2_grpc.py
nibiru_proto/cosmos/auth/v1beta1/auth_pb2.py
nibiru_proto/cosmos/auth/v1beta1/auth_pb2.pyi
nibiru_proto/cosmos/auth/v1beta1/auth_pb2_grpc.py
nibiru_proto/cosmos/auth/v1beta1/genesis_pb2.py
nibiru-0.21.12.dist-info/LICENSE
nibiru-0.21.12.dist-info/WHEEL
nibiru-0.21.12.dist-info/METADATA
nibiru-0.21.12.dist-info/RECORD
