Metadata-Version: 2.1
Name: nibiru
Version: 0.21.12
Summary: Python SDK for interacting with Nibiru.
Home-page: https://github.com/NibiruChain/py-sdk
License: MIT
Keywords: nibiru,blockchain,sdk,python,cosmos
Author: Nibiru Chain
Author-email: dev@nibiru.fi
Maintainer: NibiruHeisenberg
Maintainer-email: dev@nibiru.fi
Requires-Python: >=3.8.16,<4.0.0
Classifier: Intended Audience :: Developers
Classifier: License :: OSI Approved :: MIT License
Classifier: Programming Language :: Python :: 3
Classifier: Programming Language :: Python :: 3.9
Classifier: Programming Language :: Python :: 3.10
Classifier: Programming Language :: Python :: 3.11
Classifier: Topic :: Software Development :: Libraries :: Python Modules
Requires-Dist: bech32 (>=1.2.0,<2.0.0)
Requires-Dist: bip32 (>=3.4,<4.0)
Requires-Dist: ecdsa (>=0.18.0,<0.19.0)
Requires-Dist: grpcio (>=1.58.0,<2.0.0)
Requires-Dist: mnemonic (>=0.20,<0.21)
Requires-Dist: packaging (>=23.1,<24.0)
Requires-Dist: protobuf (>=4.24.3,<5.0.0)
Requires-Dist: python-dotenv (>=1.0.0,<2.0.0)
Requires-Dist: requests (>=2.31.0,<3.0.0)
Requires-Dist: websocket-client (>=1.6.3,<2.0.0)
Project-URL: Repository, https://github.com/NibiruChain/py-sdk
